modred/__init__.py
modred/_version.py
modred/bpod.py
modred/dmd.py
modred/era.py
modred/ltigalerkinproj.py
modred/okid.py
modred/parallel.py
modred/pod.py
modred/reductions.py
modred/util.py
modred/vectors.py
modred/vectorspace.py
modred/examples/__init__.py
modred/examples/customvector.py
modred/examples/hermite.py
modred/examples/main_CGL.py
modred/examples/rom_ex1.py
modred/examples/rom_ex2.py
modred/examples/runall.py
modred/examples/tutorial_ex1.py
modred/examples/tutorial_ex2.py
modred/examples/tutorial_ex3.py
modred/examples/tutorial_ex4.py
modred/examples/tutorial_ex5.py
modred/examples/tutorial_ex6.py
modred/tests/__init__.py
modred/tests/alltests.py
modred/tests/benchmark.py
modred/tests/helper.py
modred/tests/load_prof_parallel.py
modred/tests/scaling.py
modred/tests/testbpod.py
modred/tests/testdmd.py
modred/tests/testera.py
modred/tests/testexamples.py
modred/tests/testltigalerkinproj.py
modred/tests/testokid.py
modred/tests/testparallel.py
modred/tests/testpod.py
modred/tests/testutil.py
modred/tests/testvectors.py
modred/tests/testvectorspace.py
modred-2.0.1.dist-info/DESCRIPTION.rst
modred-2.0.1.dist-info/METADATA
modred-2.0.1.dist-info/RECORD
modred-2.0.1.dist-info/WHEEL
modred-2.0.1.dist-info/metadata.json
modred-2.0.1.dist-info/pbr.json
modred-2.0.1.dist-info/top_level.txt
