Metadata-Version: 2.0
Name: modred
Version: 2.0.1
Summary: Compute modal decompositions and reduced-order models, easily, efficiently, and in parallel.
Home-page: https://pythonhosted.org/modred
Author: Brandt Belson, Jonathan Tu, and Clancy Rowley;repacked and ported for Python 3 by Pierre Augier
Author-email: bbelson@princeton.edu
License: Free BSD
Platform: UNKNOWN
Classifier: Development Status :: 5 - Production/Stable
Classifier: Intended Audience :: Science/Research
Classifier: Intended Audience :: Education
Classifier: Topic :: Scientific/Engineering
Classifier: License :: OSI Approved :: BSD License
Classifier: Programming Language :: Python
Classifier: Programming Language :: Python :: 2
Classifier: Programming Language :: Python :: 2.7
Classifier: Programming Language :: Python :: 3
Classifier: Programming Language :: Python :: 3.3
Classifier: Programming Language :: Python :: 3.4
Requires-Dist: future
Requires-Dist: numpy
